{
 "generated_at": "2026-07-23T10:17:32+09:00",
 "target_session": "2026-07-24",
 "auction_starts": "2026-07-23 19:30",
 "status": "ok",
 "completeness": 0.729,
 "items": [
  {
   "item": "대파(일반)",
   "last_session": "2026-07-23",
   "target_session": "2026-07-24",
   "prev": 105850.0,
   "point": 141202.78738499965,
   "lo": 106639.0148583639,
   "hi": 186576.00012654273,
   "naive": 105850.0,
   "naive_c": 101933.55,
   "n_train": 3799
  },
  {
   "item": "양배추(일반)",
   "last_session": "2026-07-23",
   "target_session": "2026-07-24",
   "prev": 211232.0,
   "point": 210490.9267513323,
   "lo": 167063.5812912777,
   "hi": 258064.41329545208,
   "naive": 211232.0,
   "naive_c": 199931.088,
   "n_train": 2172
  },
  {
   "item": "저장무",
   "last_session": "2026-07-23",
   "target_session": "2026-07-24",
   "prev": 17880.0,
   "point": 15150.424752661189,
   "lo": 9497.790434167628,
   "hi": 27299.288363460393,
   "naive": 17880.0,
   "naive_c": 16092.0,
   "n_train": 1753
  },
  {
   "item": "깐쪽파",
   "last_session": "2026-07-23",
   "target_session": "2026-07-24",
   "prev": 3371.0,
   "point": 3219.7086391428516,
   "lo": 2490.062289133853,
   "hi": 3831.113643218147,
   "naive": 3371.0,
   "naive_c": 3222.6760000000004,
   "n_train": 3799
  },
  {
   "item": "여름무",
   "last_session": "2026-07-23",
   "target_session": "2026-07-24",
   "prev": 229800.0,
   "point": 350049.8858341809,
   "lo": 210457.58510544736,
   "hi": 621452.5894316996,
   "naive": 229800.0,
   "naive_c": 206820.0,
   "n_train": 327
  },
  {
   "item": "여름배추",
   "last_session": "2026-07-23",
   "target_session": "2026-07-24",
   "prev": 211570.0,
   "point": 282021.6021060711,
   "lo": 195554.2821567935,
   "hi": 559169.2158164006,
   "naive": 211570.0,
   "naive_c": 190413.0,
   "n_train": 327
  },
  {
   "item": "찰옥수수",
   "last_session": "2026-07-23",
   "target_session": "2026-07-24",
   "prev": 72288.0,
   "point": 78181.47855378326,
   "lo": 46583.234926975674,
   "hi": 89553.59023014936,
   "naive": 72288.0,
   "naive_c": 65059.200000000004,
   "n_train": 1165
  },
  {
   "item": "쪽파(일반)",
   "last_session": "2026-07-23",
   "target_session": "2026-07-24",
   "prev": 2020.0,
   "point": 2082.915136806997,
   "lo": 1466.453690383477,
   "hi": 3087.644143371095,
   "naive": 2020.0,
   "naive_c": 1821.03,
   "n_train": 1277
  }
 ],
 "total_point": 1082399.7291589782,
 "total_prev": 854011.0
}