{"item":"봄배추","amount_eok":931,"mape_naive":32.5,"mape_ridge":30.5,"improve":6.2,"dm_p":0.4785,"series":[{"d":"2024-06-17","actual":321.5,"lo":209.5,"mid":340.7,"hi":469.1},{"d":"2024-06-18","actual":414.1,"lo":250.9,"mid":311.9,"hi":383.4},{"d":"2024-06-19","actual":316.3,"lo":251.8,"mid":312.9,"hi":421.8},{"d":"2024-06-20","actual":362.4,"lo":265.6,"mid":339.0,"hi":416.8},{"d":"2024-06-21","actual":275.2,"lo":223.0,"mid":310.5,"hi":391.6},{"d":"2024-06-22","actual":268.0,"lo":170.5,"mid":308.6,"hi":381.1},{"d":"2024-06-24","actual":300.6,"lo":288.1,"mid":375.1,"hi":480.7},{"d":"2024-06-25","actual":300.5,"lo":236.3,"mid":311.6,"hi":388.9},{"d":"2024-06-26","actual":379.4,"lo":236.6,"mid":317.2,"hi":382.5},{"d":"2024-06-27","actual":383.1,"lo":232.7,"mid":326.9,"hi":435.3},{"d":"2024-06-28","actual":287.1,"lo":264.4,"mid":349.4,"hi":435.6},{"d":"2024-06-29","actual":309.6,"lo":210.5,"mid":345.1,"hi":426.6},{"d":"2025-04-28","actual":64.4,"lo":13.5,"mid":36.2,"hi":107.7},{"d":"2025-04-29","actual":103.9,"lo":31.1,"mid":71.9,"hi":197.2},{"d":"2025-04-30","actual":53.8,"lo":60.3,"mid":111.6,"hi":192.0},{"d":"2025-05-01","actual":78.1,"lo":47.7,"mid":91.4,"hi":156.3},{"d":"2025-05-02","actual":169.2,"lo":69.2,"mid":104.9,"hi":155.9},{"d":"2025-05-03","actual":132.9,"lo":68.7,"mid":137.4,"hi":211.3},{"d":"2025-05-05","actual":189.3,"lo":98.7,"mid":204.6,"hi":283.7},{"d":"2025-05-06","actual":219.4,"lo":99.2,"mid":175.8,"hi":255.1},{"d":"2025-05-07","actual":190.3,"lo":136.9,"mid":189.0,"hi":261.4},{"d":"2025-05-08","actual":183.4,"lo":170.6,"mid":247.6,"hi":288.8},{"d":"2025-05-09","actual":169.0,"lo":155.4,"mid":237.2,"hi":278.4},{"d":"2025-05-10","actual":189.5,"lo":116.0,"mid":190.2,"hi":228.0},{"d":"2025-05-12","actual":211.3,"lo":135.4,"mid":224.9,"hi":319.5},{"d":"2025-05-13","actual":208.2,"lo":142.6,"mid":211.6,"hi":284.1},{"d":"2025-05-14","actual":249.6,"lo":164.3,"mid":235.1,"hi":281.8},{"d":"2025-05-15","actual":260.7,"lo":180.0,"mid":247.2,"hi":313.4},{"d":"2025-05-16","actual":229.4,"lo":146.1,"mid":215.7,"hi":290.2},{"d":"2025-05-17","actual":137.7,"lo":114.9,"mid":183.2,"hi":244.2},{"d":"2025-05-19","actual":251.5,"lo":158.0,"mid":279.8,"hi":469.4},{"d":"2025-05-20","actual":229.8,"lo":206.4,"mid":280.7,"hi":330.3},{"d":"2025-05-21","actual":221.1,"lo":218.2,"mid":257.8,"hi":312.6},{"d":"2025-05-22","actual":229.3,"lo":171.8,"mid":227.4,"hi":282.9},{"d":"2025-05-23","actual":254.1,"lo":171.1,"mid":220.2,"hi":285.6},{"d":"2025-05-24","actual":196.0,"lo":122.9,"mid":195.0,"hi":258.6},{"d":"2025-05-26","actual":299.8,"lo":206.9,"mid":286.4,"hi":385.7},{"d":"2025-05-27","actual":268.8,"lo":251.5,"mid":304.8,"hi":390.7},{"d":"2025-05-28","actual":290.3,"lo":218.4,"mid":272.6,"hi":336.1},{"d":"2025-05-29","actual":276.8,"lo":229.9,"mid":296.1,"hi":367.3},{"d":"2025-05-30","actual":262.3,"lo":198.4,"mid":283.9,"hi":369.2},{"d":"2025-05-31","actual":231.4,"lo":170.2,"mid":243.2,"hi":338.7},{"d":"2025-06-02","actual":310.4,"lo":238.1,"mid":318.3,"hi":439.3},{"d":"2025-06-03","actual":291.9,"lo":239.3,"mid":317.3,"hi":420.1},{"d":"2025-06-04","actual":227.7,"lo":212.3,"mid":261.5,"hi":353.3},{"d":"2025-06-05","actual":305.6,"lo":219.9,"mid":284.8,"hi":384.8},{"d":"2025-06-06","actual":244.0,"lo":178.2,"mid":261.1,"hi":356.2},{"d":"2025-06-07","actual":210.9,"lo":142.5,"mid":226.9,"hi":278.6},{"d":"2025-06-09","actual":298.0,"lo":236.4,"mid":306.8,"hi":425.1},{"d":"2025-06-10","actual":300.3,"lo":230.3,"mid":292.9,"hi":378.2},{"d":"2025-06-11","actual":261.9,"lo":226.5,"mid":276.1,"hi":351.3},{"d":"2025-06-12","actual":223.3,"lo":199.9,"mid":285.5,"hi":370.0},{"d":"2025-06-13","actual":252.0,"lo":216.3,"mid":252.2,"hi":334.9},{"d":"2025-06-14","actual":230.8,"lo":157.8,"mid":226.0,"hi":300.0},{"d":"2025-06-16","actual":527.9,"lo":244.0,"mid":309.5,"hi":467.5},{"d":"2025-06-17","actual":239.1,"lo":263.0,"mid":400.8,"hi":581.9},{"d":"2025-06-18","actual":310.5,"lo":214.5,"mid":284.1,"hi":386.0},{"d":"2025-06-19","actual":264.3,"lo":195.3,"mid":278.7,"hi":451.9},{"d":"2025-06-20","actual":255.2,"lo":183.0,"mid":265.1,"hi":317.8},{"d":"2025-06-21","actual":172.6,"lo":162.9,"mid":248.6,"hi":303.2},{"d":"2025-06-23","actual":307.0,"lo":209.6,"mid":349.9,"hi":589.3},{"d":"2025-06-24","actual":286.9,"lo":170.5,"mid":238.4,"hi":329.7},{"d":"2025-06-25","actual":383.4,"lo":195.8,"mid":267.2,"hi":322.4},{"d":"2025-06-26","actual":139.7,"lo":233.6,"mid":319.7,"hi":399.9},{"d":"2025-06-27","actual":247.0,"lo":141.0,"mid":250.1,"hi":476.9},{"d":"2025-06-28","actual":226.7,"lo":130.3,"mid":207.9,"hi":342.0},{"d":"2025-06-30","actual":287.8,"lo":211.4,"mid":281.0,"hi":396.0},{"d":"2026-04-29","actual":1.5,"lo":8.2,"mid":21.0,"hi":61.0},{"d":"2026-04-30","actual":39.8,"lo":0.9,"mid":2.1,"hi":5.5},{"d":"2026-05-01","actual":60.1,"lo":20.6,"mid":39.5,"hi":96.2},{"d":"2026-05-02","actual":20.1,"lo":25.4,"mid":54.5,"hi":113.3},{"d":"2026-05-04","actual":134.9,"lo":24.6,"mid":47.5,"hi":100.1},{"d":"2026-05-05","actual":180.6,"lo":72.5,"mid":149.5,"hi":232.0},{"d":"2026-05-06","actual":129.2,"lo":84.7,"mid":169.5,"hi":250.8},{"d":"2026-05-07","actual":142.5,"lo":113.2,"mid":181.2,"hi":243.8},{"d":"2026-05-08","actual":104.6,"lo":87.3,"mid":138.4,"hi":184.2},{"d":"2026-05-09","actual":126.4,"lo":75.1,"mid":151.5,"hi":181.8},{"d":"2026-05-11","actual":143.4,"lo":86.0,"mid":163.9,"hi":222.5},{"d":"2026-05-12","actual":174.3,"lo":116.0,"mid":171.6,"hi":197.4},{"d":"2026-05-13","actual":129.2,"lo":122.9,"mid":175.4,"hi":227.9},{"d":"2026-05-14","actual":107.7,"lo":136.1,"mid":209.3,"hi":277.2},{"d":"2026-05-15","actual":119.3,"lo":117.4,"mid":179.7,"hi":263.8},{"d":"2026-05-16","actual":136.2,"lo":82.3,"mid":140.4,"hi":183.8},{"d":"2026-05-18","actual":96.7,"lo":86.5,"mid":159.4,"hi":220.6},{"d":"2026-05-19","actual":143.1,"lo":105.0,"mid":175.9,"hi":247.6},{"d":"2026-05-20","actual":154.5,"lo":86.6,"mid":140.9,"hi":181.1},{"d":"2026-05-21","actual":135.3,"lo":94.7,"mid":153.8,"hi":180.7},{"d":"2026-05-22","actual":121.5,"lo":103.1,"mid":152.4,"hi":183.9},{"d":"2026-05-23","actual":145.1,"lo":72.4,"mid":108.9,"hi":145.3},{"d":"2026-05-25","actual":200.4,"lo":102.1,"mid":172.8,"hi":213.7},{"d":"2026-05-26","actual":201.4,"lo":165.1,"mid":211.6,"hi":246.1},{"d":"2026-05-27","actual":167.1,"lo":179.9,"mid":236.1,"hi":264.7},{"d":"2026-05-28","actual":228.9,"lo":140.3,"mid":216.3,"hi":243.8},{"d":"2026-05-29","actual":155.1,"lo":132.7,"mid":178.8,"hi":245.0},{"d":"2026-05-30","actual":173.3,"lo":109.4,"mid":179.3,"hi":236.8},{"d":"2026-06-01","actual":196.8,"lo":150.8,"mid":202.9,"hi":276.1},{"d":"2026-06-02","actual":269.0,"lo":165.4,"mid":222.6,"hi":251.1},{"d":"2026-06-04","actual":275.4,"lo":207.6,"mid":285.7,"hi":344.3},{"d":"2026-06-05","actual":249.4,"lo":207.0,"mid":266.4,"hi":341.4},{"d":"2026-06-06","actual":129.4,"lo":135.7,"mid":199.8,"hi":275.6},{"d":"2026-06-08","actual":281.4,"lo":164.2,"mid":289.1,"hi":515.6},{"d":"2026-06-09","actual":156.9,"lo":148.9,"mid":229.2,"hi":300.9},{"d":"2026-06-10","actual":240.1,"lo":167.4,"mid":237.2,"hi":334.7},{"d":"2026-06-11","actual":289.0,"lo":160.4,"mid":224.1,"hi":287.5},{"d":"2026-06-12","actual":189.6,"lo":173.9,"mid":236.0,"hi":296.6},{"d":"2026-06-13","actual":208.9,"lo":138.4,"mid":246.0,"hi":317.5},{"d":"2026-06-15","actual":223.5,"lo":179.1,"mid":254.7,"hi":307.8},{"d":"2026-06-16","actual":250.7,"lo":191.2,"mid":245.4,"hi":284.9},{"d":"2026-06-17","actual":291.4,"lo":178.3,"mid":228.2,"hi":290.4},{"d":"2026-06-18","actual":303.2,"lo":179.9,"mid":232.6,"hi":310.3},{"d":"2026-06-19","actual":123.2,"lo":199.5,"mid":255.7,"hi":304.7},{"d":"2026-06-20","actual":247.0,"lo":105.1,"mid":218.8,"hi":401.8},{"d":"2026-06-22","actual":264.2,"lo":159.2,"mid":266.5,"hi":370.1},{"d":"2026-06-23","actual":346.9,"lo":177.3,"mid":271.3,"hi":319.1},{"d":"2026-06-24","actual":308.0,"lo":187.3,"mid":264.1,"hi":359.0},{"d":"2026-06-25","actual":235.2,"lo":189.0,"mid":274.7,"hi":341.1},{"d":"2026-06-26","actual":281.6,"lo":198.1,"mid":277.2,"hi":361.8},{"d":"2026-06-27","actual":153.5,"lo":155.4,"mid":236.1,"hi":306.3},{"d":"2026-06-29","actual":386.8,"lo":188.4,"mid":343.9,"hi":608.4},{"d":"2026-06-30","actual":314.7,"lo":217.8,"mid":301.3,"hi":438.8}]}