{"item":"봄무","amount_eok":621,"mape_naive":53.7,"mape_ridge":52.2,"improve":2.9,"dm_p":0.4303,"series":[{"d":"2024-05-28","actual":106.6,"lo":73.3,"mid":118.3,"hi":190.0},{"d":"2024-05-29","actual":77.8,"lo":61.8,"mid":116.3,"hi":162.6},{"d":"2024-05-30","actual":146.6,"lo":58.3,"mid":95.3,"hi":166.6},{"d":"2024-05-31","actual":197.9,"lo":78.8,"mid":120.6,"hi":198.2},{"d":"2024-06-01","actual":177.9,"lo":97.6,"mid":151.7,"hi":248.1},{"d":"2024-06-03","actual":211.4,"lo":110.5,"mid":204.4,"hi":286.4},{"d":"2024-06-04","actual":152.2,"lo":135.9,"mid":182.3,"hi":277.5},{"d":"2024-06-05","actual":183.1,"lo":146.3,"mid":239.4,"hi":345.4},{"d":"2024-06-06","actual":282.0,"lo":142.1,"mid":207.2,"hi":340.8},{"d":"2024-06-07","actual":353.5,"lo":177.0,"mid":241.5,"hi":382.5},{"d":"2024-06-08","actual":275.3,"lo":182.4,"mid":252.6,"hi":438.6},{"d":"2024-06-10","actual":303.3,"lo":211.0,"mid":339.5,"hi":468.4},{"d":"2024-06-11","actual":355.0,"lo":235.2,"mid":305.5,"hi":399.2},{"d":"2024-06-12","actual":220.2,"lo":233.1,"mid":303.8,"hi":415.3},{"d":"2024-06-13","actual":204.8,"lo":193.8,"mid":293.2,"hi":390.9},{"d":"2024-06-14","actual":219.7,"lo":172.3,"mid":236.4,"hi":327.2},{"d":"2024-06-15","actual":262.9,"lo":172.7,"mid":226.4,"hi":358.9},{"d":"2024-06-17","actual":362.8,"lo":185.3,"mid":306.8,"hi":442.4},{"d":"2024-06-18","actual":275.0,"lo":226.7,"mid":309.6,"hi":437.5},{"d":"2024-06-19","actual":350.2,"lo":244.6,"mid":306.6,"hi":467.7},{"d":"2024-06-20","actual":329.0,"lo":250.2,"mid":340.9,"hi":498.0},{"d":"2024-06-21","actual":307.1,"lo":248.7,"mid":297.3,"hi":420.4},{"d":"2024-06-22","actual":462.3,"lo":255.1,"mid":327.0,"hi":467.6},{"d":"2024-06-24","actual":406.5,"lo":315.9,"mid":511.3,"hi":678.7},{"d":"2024-06-25","actual":399.0,"lo":298.3,"mid":371.6,"hi":526.5},{"d":"2024-06-26","actual":426.4,"lo":318.0,"mid":392.2,"hi":487.0},{"d":"2024-06-27","actual":397.1,"lo":280.0,"mid":330.6,"hi":477.0},{"d":"2024-06-28","actual":428.2,"lo":287.7,"mid":350.4,"hi":501.1},{"d":"2024-06-29","actual":341.1,"lo":281.1,"mid":380.2,"hi":613.7},{"d":"2025-05-03","actual":11.6,"lo":10.9,"mid":21.7,"hi":92.3},{"d":"2025-05-12","actual":7.2,"lo":6.6,"mid":14.8,"hi":51.7},{"d":"2025-05-13","actual":58.9,"lo":4.8,"mid":10.3,"hi":28.9},{"d":"2025-05-14","actual":51.8,"lo":37.1,"mid":63.4,"hi":169.7},{"d":"2025-05-15","actual":82.1,"lo":31.8,"mid":55.5,"hi":122.1},{"d":"2025-05-16","actual":54.0,"lo":35.6,"mid":59.1,"hi":123.8},{"d":"2025-05-17","actual":33.8,"lo":28.2,"mid":64.9,"hi":139.2},{"d":"2025-05-19","actual":162.2,"lo":30.0,"mid":86.9,"hi":170.8},{"d":"2025-05-20","actual":163.3,"lo":94.2,"mid":152.1,"hi":287.1},{"d":"2025-05-21","actual":170.3,"lo":86.6,"mid":151.8,"hi":223.1},{"d":"2025-05-22","actual":168.2,"lo":92.7,"mid":157.1,"hi":241.0},{"d":"2025-05-23","actual":160.3,"lo":84.0,"mid":130.0,"hi":217.4},{"d":"2025-05-24","actual":160.2,"lo":79.7,"mid":141.9,"hi":219.8},{"d":"2025-05-26","actual":259.3,"lo":90.3,"mid":208.7,"hi":265.7},{"d":"2025-05-27","actual":217.4,"lo":178.8,"mid":277.2,"hi":366.1},{"d":"2025-05-28","actual":228.8,"lo":158.0,"mid":268.0,"hi":361.5},{"d":"2025-05-29","actual":304.9,"lo":211.0,"mid":316.1,"hi":477.6},{"d":"2025-05-30","actual":316.9,"lo":213.8,"mid":290.4,"hi":512.5},{"d":"2025-05-31","actual":373.3,"lo":211.7,"mid":303.2,"hi":413.2},{"d":"2025-06-02","actual":445.2,"lo":203.3,"mid":374.4,"hi":538.7},{"d":"2025-06-03","actual":212.9,"lo":230.3,"mid":324.0,"hi":472.2},{"d":"2025-06-04","actual":120.5,"lo":194.1,"mid":321.9,"hi":456.6},{"d":"2025-06-05","actual":354.7,"lo":129.2,"mid":227.9,"hi":401.6},{"d":"2025-06-06","actual":408.5,"lo":273.0,"mid":344.6,"hi":600.4},{"d":"2025-06-07","actual":277.4,"lo":214.1,"mid":300.9,"hi":462.3},{"d":"2025-06-09","actual":291.7,"lo":247.6,"mid":458.7,"hi":567.5},{"d":"2025-06-10","actual":327.3,"lo":257.6,"mid":357.4,"hi":472.0},{"d":"2025-06-11","actual":240.1,"lo":194.3,"mid":258.5,"hi":365.7},{"d":"2025-06-12","actual":323.9,"lo":189.5,"mid":318.6,"hi":374.4},{"d":"2025-06-13","actual":324.8,"lo":223.2,"mid":329.5,"hi":428.6},{"d":"2025-06-14","actual":263.8,"lo":208.2,"mid":301.3,"hi":404.4},{"d":"2025-06-16","actual":435.9,"lo":285.6,"mid":490.5,"hi":636.6},{"d":"2025-06-17","actual":399.0,"lo":351.5,"mid":400.4,"hi":621.1},{"d":"2025-06-18","actual":449.7,"lo":230.7,"mid":309.4,"hi":438.2},{"d":"2025-06-19","actual":302.0,"lo":246.3,"mid":314.7,"hi":467.9},{"d":"2025-06-20","actual":297.5,"lo":228.9,"mid":332.4,"hi":443.7},{"d":"2025-06-21","actual":281.9,"lo":237.0,"mid":345.2,"hi":526.0},{"d":"2025-06-23","actual":389.4,"lo":240.9,"mid":383.5,"hi":592.4},{"d":"2025-06-24","actual":418.4,"lo":188.7,"mid":266.2,"hi":392.0},{"d":"2025-06-25","actual":352.8,"lo":200.8,"mid":281.0,"hi":438.7},{"d":"2025-06-26","actual":176.5,"lo":226.0,"mid":294.0,"hi":423.8},{"d":"2025-06-27","actual":455.6,"lo":154.1,"mid":300.3,"hi":627.6},{"d":"2025-06-28","actual":344.1,"lo":228.5,"mid":335.3,"hi":531.2},{"d":"2025-06-30","actual":338.2,"lo":200.9,"mid":342.4,"hi":516.3},{"d":"2026-05-07","actual":31.4,"lo":22.1,"mid":34.9,"hi":139.3},{"d":"2026-05-08","actual":10.0,"lo":19.9,"mid":31.8,"hi":96.7},{"d":"2026-05-09","actual":10.0,"lo":7.7,"mid":14.5,"hi":37.8},{"d":"2026-05-11","actual":20.0,"lo":9.2,"mid":22.5,"hi":45.8},{"d":"2026-05-12","actual":18.3,"lo":14.0,"mid":27.5,"hi":50.3},{"d":"2026-05-13","actual":15.5,"lo":13.2,"mid":24.4,"hi":48.3},{"d":"2026-05-14","actual":29.8,"lo":11.1,"mid":23.7,"hi":37.3},{"d":"2026-05-15","actual":32.9,"lo":15.4,"mid":30.4,"hi":60.5},{"d":"2026-05-16","actual":11.7,"lo":15.5,"mid":33.4,"hi":60.6},{"d":"2026-05-18","actual":112.3,"lo":11.7,"mid":28.6,"hi":55.6},{"d":"2026-05-19","actual":85.5,"lo":50.9,"mid":88.1,"hi":139.4},{"d":"2026-05-20","actual":81.3,"lo":42.5,"mid":87.2,"hi":131.2},{"d":"2026-05-21","actual":122.6,"lo":52.1,"mid":103.1,"hi":153.2},{"d":"2026-05-22","actual":96.0,"lo":67.0,"mid":125.1,"hi":184.7},{"d":"2026-05-23","actual":139.5,"lo":43.1,"mid":106.7,"hi":141.2},{"d":"2026-05-25","actual":113.8,"lo":83.9,"mid":170.1,"hi":237.6},{"d":"2026-05-26","actual":168.4,"lo":89.8,"mid":169.4,"hi":221.0},{"d":"2026-05-27","actual":201.8,"lo":128.8,"mid":190.7,"hi":289.8},{"d":"2026-05-28","actual":80.4,"lo":107.1,"mid":165.7,"hi":251.2},{"d":"2026-05-29","actual":253.8,"lo":62.1,"mid":134.1,"hi":200.9},{"d":"2026-05-30","actual":184.3,"lo":136.7,"mid":224.4,"hi":347.3},{"d":"2026-06-01","actual":412.6,"lo":151.8,"mid":288.2,"hi":319.1},{"d":"2026-06-02","actual":277.8,"lo":221.2,"mid":326.6,"hi":455.0},{"d":"2026-06-04","actual":210.7,"lo":212.4,"mid":396.5,"hi":469.6},{"d":"2026-06-05","actual":275.0,"lo":206.6,"mid":329.7,"hi":470.0},{"d":"2026-06-06","actual":387.5,"lo":205.5,"mid":293.2,"hi":396.2},{"d":"2026-06-08","actual":316.6,"lo":228.7,"mid":349.4,"hi":501.7},{"d":"2026-06-09","actual":303.1,"lo":205.2,"mid":325.2,"hi":381.1},{"d":"2026-06-10","actual":212.7,"lo":221.8,"mid":330.8,"hi":371.8},{"d":"2026-06-11","actual":178.7,"lo":176.1,"mid":341.0,"hi":345.6},{"d":"2026-06-12","actual":255.7,"lo":170.9,"mid":287.8,"hi":389.5},{"d":"2026-06-13","actual":343.8,"lo":218.6,"mid":304.3,"hi":473.4},{"d":"2026-06-15","actual":354.3,"lo":256.9,"mid":356.8,"hi":480.5},{"d":"2026-06-16","actual":387.4,"lo":245.0,"mid":364.7,"hi":429.1},{"d":"2026-06-17","actual":452.4,"lo":322.3,"mid":412.1,"hi":517.6},{"d":"2026-06-18","actual":403.5,"lo":282.5,"mid":362.2,"hi":473.5},{"d":"2026-06-19","actual":282.4,"lo":216.0,"mid":335.0,"hi":435.3},{"d":"2026-06-20","actual":293.3,"lo":226.1,"mid":350.7,"hi":405.2},{"d":"2026-06-22","actual":208.3,"lo":255.0,"mid":390.8,"hi":457.6},{"d":"2026-06-23","actual":382.0,"lo":208.6,"mid":350.0,"hi":493.5},{"d":"2026-06-24","actual":322.0,"lo":222.6,"mid":295.1,"hi":454.5},{"d":"2026-06-25","actual":328.7,"lo":192.5,"mid":276.8,"hi":387.4},{"d":"2026-06-26","actual":445.9,"lo":212.8,"mid":286.8,"hi":393.4},{"d":"2026-06-27","actual":354.9,"lo":209.6,"mid":310.4,"hi":445.1},{"d":"2026-06-29","actual":252.2,"lo":197.2,"mid":326.1,"hi":501.4},{"d":"2026-06-30","actual":314.8,"lo":243.5,"mid":393.4,"hi":523.9},{"d":"2026-07-01","actual":6.1,"lo":248.5,"mid":293.6,"hi":462.7}]}